micromechanics/__init__.py
micromechanics/indentation/__init__.py
micromechanics/indentation/calibration.py
micromechanics/indentation/definitions.py
micromechanics/indentation/hertz.py
micromechanics/indentation/input.py
micromechanics/indentation/main.py
micromechanics/indentation/plot.py
micromechanics/indentation/seldomUsedFunctions.py
micromechanics/indentation/terms.json
micromechanics/indentation/theory.py
micromechanics/indentation/tip.py
micromechanics/indentation/verification.py
micromechanics/tif/OpenSans-Regular.ttf
micromechanics/tif/__init__.py
micromechanics-1.1.21.dist-info/LICENSE
micromechanics-1.1.21.dist-info/METADATA
micromechanics-1.1.21.dist-info/WHEEL
micromechanics-1.1.21.dist-info/top_level.txt
micromechanics-1.1.21.dist-info/RECORD
