Metadata-Version: 2.1
Name: micromechanics
Version: 1.1.21
Summary: Investigation of nanoindentation and SEM data
Home-page: https://micromechanics.github.io/micromechanics/
Author: Micromechanics Team and Steffen Brinckmann
Author-email: sbrinckm@gmail.com
License: MIT
Platform: UNKNOWN
Classifier: Programming Language :: Python
Classifier: License :: OSI Approved :: BSD License
Classifier: Programming Language :: Python :: 3
Requires-Python: >=3.7
License-File: LICENSE
Requires-Dist: h5py
Requires-Dist: lmfit
Requires-Dist: matplotlib
Requires-Dist: numpy
Requires-Dist: opencv-python
Requires-Dist: pandas
Requires-Dist: scikit-image
Requires-Dist: scipy
Requires-Dist: xlrd
